pharus/__init__.py
pharus/component_interface.py
pharus/dynamic_api_gen.py
pharus/error.py
pharus/interface.py
pharus/server.py
pharus/version.py
pharus-0.8.12.dist-info/LICENSE
pharus-0.8.12.dist-info/METADATA
pharus-0.8.12.dist-info/WHEEL
pharus-0.8.12.dist-info/entry_points.txt
pharus-0.8.12.dist-info/top_level.txt
pharus-0.8.12.dist-info/RECORD
