Metadata-Version: 2.1
Name: pharus
Version: 0.8.12
Summary: A generic REST API server backend for DataJoint pipelines.
Home-page: https://github.com/datajoint/pharus
Author: DataJoint Neuro
Author-email: support@vathes.com
Classifier: Programming Language :: Python :: 3
Classifier: Operating System :: OS Independent
License-File: LICENSE
Requires-Dist: flask (>=2.2.2)
Requires-Dist: gunicorn
Requires-Dist: pyjwt[crypto]
Requires-Dist: datajoint (>=0.13.0)
Requires-Dist: datajoint-connection-hub
Requires-Dist: pyyaml
Requires-Dist: envyaml
Requires-Dist: otumat (>=0.3.1)
Requires-Dist: numpy
Requires-Dist: requests
Requires-Dist: opencv-python-headless
